{"overview":"Trận Long Tân có thể là trận đánh nổi tiếng nhất của quân đội Úc trong chiến tranh Việt Nam. Cuộc đụng độ này xảy ra vào hai ngày 18 và 19 tháng 8 năm 1966 tại một khu rừng cao su gần xã Long Tân, tỉnh Phước Tuy (nay là xã Long Tân, huyện Đất Đỏ, tỉnh Bà Rịa \u2013 Vũng Tàu). Đây là lần duy nhất trong toàn cuộc chiến Quân đội Úc đơn phương đối đầu với Quân Giải phóng miền Nam Việt Nam, trận chiến này Quân đội Úc sử dụng ưu thế hỏa lực của pháo binh (Quân Úc có tới 24 khẩu pháo các loại, trong đó bao gồm 18 khẩu pháo L-5 cỡ nòng 105mm và 6 khẩu M-109 cỡ nòng 155mm) kết hợp với máy bay (2 chiếc trực thăng UH-1, 1 chiếc H-13 Sioux và 3 chiếc F4 Phantom) yểm trợ khiến Quân Giải phóng bị thiệt hại nhiều ","aliases":[],"references":{"năm trong lịch":[{"type":"string","value":"1966"}],"người":[{"id":"Q10799489","type":"wikibase-item","value":"Nguyễn Thanh Hồng"}],"xã của Việt Nam":[{"type":"string","value":"Long Tân"}],"huyện":[{"type":"string","value":"Đất Đỏ"}],"dịch lưu hành địa phương":[{"type":"string","value":"sốt rét"}],"chiến tranh":[{"id":"Q8740","type":"wikibase-item","value":"Chiến tranh Việt Nam"},{"type":"string","value":"Chiến tranh Đông Dương (định hướng)"}],"tổ chức có vũ trang":[{"type":"string","value":"Quân Giải phóng miền Nam Việt Nam"}],"tỉnh của Việt Nam":[{"type":"string","value":"Bà Rịa - Vũng Tàu"},{"type":"string","value":"Phước Tuy"}],"quốc gia có chủ quyền":[{"type":"string","value":"Việt Nam Cộng hòa"}]},"claims":{"cuộc xung đột của":[{"source":["DBPedia"],"type":"string","value":"Sư đoàn 5, Quân đội Nhân dân Việt Nam"}],"thời điểm":[{"source":["Wikipedia"],"type":"string","value":"ngày 18 tháng 08 năm 1966"}],"một phần của":[{"id":"Q8740","source":["Wikipedia"],"type":"wikibase-item","value":"Chiến tranh Việt Nam"}],"ngày công bố":[{"source":["DBPedia"],"type":"string","value":"ngày 18 tháng 08 năm 1966"}],"trận đánh của":[{"source":["DBPedia"],"type":"string","value":"Sư đoàn 5, Quân đội Nhân dân Việt Nam"}],"thực thể tham gia":[{"source":["Wikipedia"],"type":"string","value":"Hoa Kỳ"},{"source":["Wikipedia"],"type":"string","value":"Úc"},{"source":["Wikipedia"],"type":"string","value":"New Zealand"},{"source":["Wikipedia"],"type":"string","value":"Mặt trận Dân tộc Giải phóng miền Nam Việt Nam"},{"source":["Wikipedia"],"type":"string","value":"Việt Nam Dân chủ Cộng hòa"}],"vị trí":[{"source":["Wikipedia"],"type":"string","value":"Long Tân"},{"source":["DBPedia"],"type":"string","value":"Việt Nam Cộng hòa"}],"là một":[{"source":["Wikipedia"],"type":"string","value":"trận đánh"},{"source":["Wikipedia"],"type":"string","value":"sự kiện lịch sử"}]},"description":"","id":"Q259526","label":"Trận Long Tân"}