{"overview":"Galang (tiếng Indonesia: Pulau Galang) là một hòn đảo rộng 80 km² cự ly 25 m (40 km) về phía đông nam Batam,[1] thuộc về một nhóm ba hòn đảo gọi là Barelang (viết tắt của Batam - Rempang - Galang). Một phần của quần đảo Riau, Indonesia, Galang nằm ở phía nam của Batam và Rempang mà chính họ nằm ở phía nam của Singapore và Johor. Thành phố gần nhất với Galang là Tanjung Pinang trên Bintan, cách đó khoảng 30 phút đi thuyền. Hòn đảo được kết nối bởi cầu Barelang với Rempang và Batam.","aliases":[],"references":{"người":[{"id":"Q10833363","type":"wikibase-item","value":"Văn Giảng"}],"tổ chức do Liên Hợp Quốc thành lập":[{"type":"string","value":"Cao ủy Liên Hợp Quốc về người tị nạn"}],"quốc gia có chủ quyền":[{"type":"string","value":"Singapore"}]},"claims":{"diện tích":[{"type":"string","value":"80 kilômét vuông"}],"tọa lạc trong hoặc bên cạnh thủy vực":[{"type":"string","value":"Biển Đông"}],"cao độ so với mực nước biển":[{"type":"string","value":"38 mét"}],"nằm trong phạm vi của khu vực hành chính":[{"type":"string","value":"Batam"}],"một phần của":[{"type":"string","value":"Riau"}],"quốc gia":[{"type":"string","value":"Indonesia"}],"là một":[{"type":"string","value":"đảo"}]},"id":"Q1491692","label":"Đảo Galang"}