{"overview":"Căn cứ Tân Sở là một di tích lịch sử tại Việt Nam.","aliases":[],"references":{},"claims":{"quốc gia":[{"source":["Wikipedia"],"type":"string","value":"Việt Nam"}],"vị trí":[{"source":["Wikipedia"],"type":"string","value":"Cam Chính, Cam Lộ, Quảng Trị"}],"loại di tích":[{"source":["Wikipedia"],"type":"string","value":"lịch sử"}],"là một":[{"source":["Wikipedia"],"type":"string","value":"di tích"}],"thời gian công nhận di tích":[{"source":["Wikipedia"],"type":"string","value":"năm 1995"}]},"description":"","id":"Q920959508X","label":"Căn cứ Tân Sở"}