{"overview":"Đặng Minh Bích (1453-1541)thọ 88 tuổi, quan nhà Lê sơ, sinh ra ở Bạch Đường nay là xã Ngọc Sơn, Lam Sơn và Bồi Sơn huyện Đô Lương, Nghệ An.","aliases":[],"references":{"chức vụ":[{"type":"string","value":"Thượng thư"}],"người":[{"id":"Q703747","type":"wikibase-item","value":"Lê Quý Đôn"}],"xã của Việt Nam":[{"type":"string","value":"Lam Sơn"}],"huyện":[{"type":"string","value":"Đô Lương"}],"tỉnh của Việt Nam":[{"type":"string","value":"Nghệ An"}],"triều đại":[{"id":"Q878276","type":"wikibase-item","value":"Nhà Lê sơ"}]},"claims":{"quốc tịch":[{"source":["Wikipedia"],"type":"string","value":"Việt Nam"}],"quốc gia":[{"source":["Wikipedia"],"type":"string","value":"Việt Nam"}],"là một":[{"source":["Wikipedia"],"type":"string","value":"người"}]},"description":"","id":"Q10841536","label":"Đặng Minh Bích"}