{"overview":"Lê Huân (sinh năm 1944) là một nghệ sĩ múa, biên đạo múa với nhiều tác phẩm kinh điển như Anh nuôi say súng, Mưu Thị Hến, Học trò xứ Quảng. Ông nguyên là Chủ tịch Hội Nghệ sĩ Múa thành phố Đà Nẵng và được nhà nước Việt Nam trao tặng danh hiệu Nghệ sĩ nhân dân.  ","aliases":["Lê Thế Huân"],"references":{"thành phố":[{"type":"string","value":"Hà Nội"}],"danh hiệu vinh dự":[{"type":"string","value":"Nghệ sĩ Nhân dân"}],"người":[{"id":"Q10825739","type":"wikibase-item","value":"Thái Ly"},{"id":"Q714924","type":"wikibase-item","value":"Phan Bội Châu"}],"viện đại học":[{"type":"string","value":"Học viện Múa Việt Nam"}],"thị xã của Việt Nam":[{"type":"string","value":"Sơn Tây"}],"giải thưởng":[{"type":"string","value":"Giải thưởng Nhà nước Việt Nam"}],"chiến tranh":[{"id":"Q8740","type":"wikibase-item","value":"Chiến tranh Việt Nam"}],"báo viết":[{"type":"string","value":"Tiền Phong"}],"quốc gia có chủ quyền":[{"type":"string","value":"Việt Nam"}],"quân khu của Việt Nam":[{"type":"string","value":"Quân khu 5, Quân đội Nhân dân Việt Nam"}]},"claims":{"trường học":[{"source":["Wikipedia"],"type":"string","value":"Học viện Múa Việt Nam"}],"giới tính":[{"source":["Wikipedia"],"type":"string","value":"nam"}],"quốc tịch":[{"source":["Wikipedia"],"type":"string","value":"Việt Nam"}],"nơi sinh":[{"source":["Wikipedia"],"type":"string","value":"Hà Nội"}],"ngày sinh":[{"source":["Wikipedia"],"type":"string","value":"năm 1944"}],"giải thưởng":[{"source":["Wikipedia"],"type":"string","value":"Giải thưởng Nhà nước Việt Nam"}],"nghề nghiệp":[{"source":["Wikipedia"],"type":"string","value":"biên đạo múa"}],"là một":[{"source":["Wikipedia"],"type":"string","value":"người"}]},"description":"biên đạo múa Việt Nam","id":"Q109430521","label":"Lê Huân"}