{"overview":"Hồ Quý Ly (chữ Hán: 胡季犛; 1336 \u2013 1407), lấy tên húy Hồ Nhất Nguyên (胡一元), là vị hoàng đế đầu tiên của nhà nước Đại Ngu trong lịch sử Việt Nam. Ông ở ngôi vị Hoàng đế từ năm 1400 đến năm 1401 tự xưng là Quốc Tổ Chương Hoàng (國祖章皇), sau đó giữ ngôi Thái thượng hoàng từ năm 1401 đến năm 1407.","aliases":["Lê Quý Ly","Hồ Quí Li"],"references":{"đơn vị hành chính":[{"type":"string","value":"Thăng Long"}],"khu vực địa lý":[{"type":"string","value":"An Nam"}],"người":[{"id":"Q711858","type":"wikibase-item","value":"Trần Duệ Tông"},{"id":"Q711456","type":"wikibase-item","value":"Trần Thánh Tông"},{"id":"Q716585","type":"wikibase-item","value":"Ngô Sĩ Liên"},{"id":"Q1274690","type":"wikibase-item","value":"An Dương Vương"},{"type":"string","value":"Minh Thành Tổ"},{"id":"Q713228","type":"wikibase-item","value":"Lý Huệ Tông"},{"id":"Q10761406","type":"wikibase-item","value":"Gia Từ hoàng hậu"},{"id":"Q10829478","type":"wikibase-item","value":"Trần Thiêm Bình"},{"id":"Q713224","type":"wikibase-item","value":"Trần Thái Tông"},{"id":"Q1033966","type":"wikibase-item","value":"Lê Duy Phường"},{"id":"Q711441","type":"wikibase-item","value":"Trần Anh Tông"},{"id":"Q10823137","type":"wikibase-item","value":"Sùng Hiền hầu"},{"id":"Q1154883","type":"wikibase-item","value":"Phan Huy Chú"},{"id":"Q855703","type":"wikibase-item","value":"Mạc Thái Tổ"},{"id":"Q6649392","type":"wikibase-item","value":"Lê Dụ Tông"},{"type":"string","value":"Khổng Tử"},{"type":"string","value":"Nguyên Vũ Tông"},{"id":"Q6507454","type":"wikibase-item","value":"Lê Phụ Trần"},{"id":"Q65049736","type":"wikibase-item","value":"Huy Ninh công chúa"},{"id":"Q379775","type":"wikibase-item","value":"Nguyễn Huệ"},{"id":"Q10800095","type":"wikibase-item","value":"Nguyễn Đa Phương"},{"id":"Q1195391","type":"wikibase-item","value":"Lê Thái Tổ"},{"id":"Q10748027","type":"wikibase-item","value":"Chu Thiên"},{"id":"Q1319976","type":"wikibase-item","value":"Tô Hiến Thành"},{"id":"Q665382","type":"wikibase-item","value":"Trần Trọng Kim"},{"id":"Q1347181","type":"wikibase-item","value":"Nguyễn Trãi"},{"id":"Q5374602","type":"wikibase-item","value":"Thuận Thiên hoàng hậu"},{"id":"Q65049730","type":"wikibase-item","value":"Đôn Từ Hoàng thái phi"},{"id":"Q3269873","type":"wikibase-item","value":"Hồ Hán Thương"},{"type":"string","value":"Hán Cao Tổ"},{"id":"Q1317979","type":"wikibase-item","value":"Lê Đại Hành"},{"type":"string","value":"Chế Bồng Nga"},{"id":"Q7833326","type":"wikibase-item","value":"Trần Thừa"},{"id":"Q711416","type":"wikibase-item","value":"Trần Minh Tông"},{"id":"Q1771050","type":"wikibase-item","value":"Lê Thánh Tông"},{"id":"Q10768982","type":"wikibase-item","value":"Hoàng Ngọc Phách"},{"id":"Q705535","type":"wikibase-item","value":"Trùng Quang Đế"},{"id":"Q6802344","type":"wikibase-item","value":"Lê Trang Tông"},{"id":"Q711408","type":"wikibase-item","value":"Lý Cao Tông"},{"id":"Q716814","type":"wikibase-item","value":"Trần Thiếu Đế"},{"id":"Q10829399","type":"wikibase-item","value":"Trần Nguyên Đán"},{"id":"Q1155303","type":"wikibase-item","value":"Huyền Trân"},{"id":"Q716533","type":"wikibase-item","value":"Trần Phế Đế"},{"id":"Q7199013","type":"wikibase-item","value":"Trần Cảo (vua)"},{"id":"Q716497","type":"wikibase-item","value":"Trần Hiến Tông"},{"id":"Q703747","type":"wikibase-item","value":"Lê Quý Đôn"},{"id":"Q716809","type":"wikibase-item","value":"Trần Dụ Tông"},{"id":"Q711635","type":"wikibase-item","value":"Trần Nghệ Tông"},{"id":"Q1033935","type":"wikibase-item","value":"Lê Thuần Tông"},{"id":"Q1033931","type":"wikibase-item","value":"Lê Thần Tông"},{"id":"Q716761","type":"wikibase-item","value":"Trần Thuận Tông"},{"id":"Q713251","type":"wikibase-item","value":"Lý Chiêu Hoàng"},{"id":"Q716481","type":"wikibase-item","value":"Dương Nhật Lễ"},{"id":"Q705877","type":"wikibase-item","value":"Giản Định Đế"},{"type":"string","value":"Gia Cát Lượng"},{"id":"Q72083","type":"wikibase-item","value":"Trần Nhơn Tông"},{"id":"Q3210967","type":"wikibase-item","value":"Phan Phu Tiên"},{"id":"Q4517182","type":"wikibase-item","value":"Lê Hy Tông"},{"id":"Q1033943","type":"wikibase-item","value":"Lê Ý Tông"},{"type":"string","value":"Hồ Nguyên Trừng"},{"id":"Q10788286","type":"wikibase-item","value":"Lưu Thúc Kiệm"}],"trang Web":[{"type":"string","value":"WorldCat"}],"khía cạnh của lịch sử":[{"type":"string","value":"Đại Nam"},{"type":"string","value":"Bắc thuộc"}],"nổi loạn":[{"id":"Q1154466","type":"wikibase-item","value":"Loạn 12 sứ quân"}],"chiến tranh":[{"id":"Q1112854","type":"wikibase-item","value":"Chiến tranh Minh - Đại Ngu"},{"id":"Q10747194","type":"wikibase-item","value":"Chiến tranh Nguyên Mông-Đại Việt lần 3"}],"tỉnh của Việt Nam":[{"type":"string","value":"Thanh Hóa"},{"type":"string","value":"Nghệ An"},{"type":"string","value":"Nam Định"},{"type":"string","value":"Lạng Sơn"},{"type":"string","value":"Hà Nam"},{"type":"string","value":"Bắc Giang"},{"type":"string","value":"Thái Bình"},{"type":"string","value":"Hà Giang"},{"type":"string","value":"Hà Tĩnh"},{"type":"string","value":"Lào Cai"}],"khu bảo tồn thiên nhiên":[{"id":"Q190060","type":"wikibase-item","value":"Thành nhà Hồ"}],"quốc gia có chủ quyền":[{"type":"string","value":"Việt Nam"},{"type":"string","value":"Trung Quốc"},{"type":"string","value":"nhà Thanh"}],"tỉnh của Trung Quốc":[{"type":"string","value":"Vân Nam"}],"cựu quốc gia":[{"type":"string","value":"Chiêm Thành"}],"xã của Việt Nam":[{"type":"string","value":"Quỳnh Lâm"},{"type":"string","value":"Hà Đông"}],"hệ chữ viết tượng hình":[{"type":"string","value":"chữ Nôm"},{"type":"string","value":"chữ Hán"}],"Di tích Việt Nam":[{"id":"Q10779416","type":"wikibase-item","value":"Khu di tích Côn Sơn - Kiếp Bạc"}],"Vườn quốc gia ở Việt Nam":[{"id":"Q11697940","type":"wikibase-item","value":"Vườn quốc gia Vũ Quang"}],"Khu tự trị Trung Quốc":[{"type":"string","value":"Quảng Tây"}],"thành phố cấp huyện":[{"type":"string","value":"Lâm An"}],"vương quốc":[{"id":"Q430309","type":"wikibase-item","value":"Đại Việt"},{"id":"Q10841128","type":"wikibase-item","value":"Đại Ngu"}],"xung đột":[{"id":"Q89930532","type":"wikibase-item","value":"Trận Bình Lệ Nguyên"}],"tiền tệ":[{"type":"string","value":"văn"}],"thành phố trực thuộc tỉnh Việt Nam":[{"type":"string","value":"Qui Nhơn"}],"họ":[{"type":"string","value":"Hồ"}],"huyện":[{"type":"string","value":"Tiên Du"},{"type":"string","value":"Diễn Châu"},{"type":"string","value":"Quỳnh Lưu"},{"type":"string","value":"Vĩnh Lộc"},{"type":"string","value":"Quốc Oai"},{"type":"string","value":"Ba Vì"},{"type":"string","value":"Nghĩa Đàn"},{"type":"string","value":"Hoằng Hóa"},{"type":"string","value":"Nam Đàn"}],"thủ đô":[{"type":"string","value":"Bắc Kinh"}],"Chùa Việt Nam":[{"id":"Q10779425","type":"wikibase-item","value":"Khu di tích nhà Trần ở Đông Triều"},{"id":"Q10748381","type":"wikibase-item","value":"Chùa Bồ Tát"},{"id":"Q10748515","type":"wikibase-item","value":"Chùa Phổ Minh"}],"Thư viện quốc gia":[{"type":"string","value":"Thư viện Quốc gia Pháp"}],"sông":[{"type":"string","value":"Sông Hồng"}],"triều đại":[{"id":"Q3111454","type":"wikibase-item","value":"Nhà Trần"},{"id":"Q2623875","type":"wikibase-item","value":"Nhà Hậu Trần"},{"id":"Q10800789","type":"wikibase-item","value":"Nhà Hậu Lê"},{"id":"Q1209047","type":"wikibase-item","value":"Nhà Hồ"},{"id":"Q878309","type":"wikibase-item","value":"Nhà Lý"},{"id":"Q1317991","type":"wikibase-item","value":"Nhà Mạc"}],"thành phố":[{"type":"string","value":"Hà Nội"}],"tác phẩm văn học":[{"type":"string","value":"Khâm định Việt sử Thông giám cương mục"},{"type":"string","value":"Đại Việt sử ký toàn thư"}],"loại thế giới quan":[{"type":"string","value":"tôn giáo"}],"kiểm soát tính nhất quán":[{"type":"string","value":"Virtual International Authority File"}],"bài danh sách Wikimedia":[{"type":"string","value":"Danh sách nhân vật liên quan với Hải Phòng"},{"type":"string","value":"Vua Việt Nam"},{"type":"string","value":"Danh sách Trạng nguyên Việt Nam"}],"tác phẩm viết":[{"type":"string","value":"Việt Nam sử lược"}],"Các vùng của Việt Nam":[{"type":"string","value":"Bắc Trung Bộ"}]},"claims":{"tôn giáo":[{"type":"string","value":"Nho giáo"}],"họ":[{"type":"string","value":"Hồ"}],"người phối ngẫu":[{"id":"Q65049736","type":"wikibase-item","value":"Huy Ninh công chúa"}],"nhà":[{"id":"Q1209047","type":"wikibase-item","value":"Nhà Hồ"}],"quốc tịch":[{"id":"Q10841128","type":"wikibase-item","value":"Đại Ngu"}],"nghề nghiệp":[{"type":"string","value":"nhà thơ"}],"là một":[{"type":"string","value":"người"}],"nơi mất":[{"id":"Q206219","type":"wikibase-item","value":"Hoàng thành Thăng Long"}],"giới tính":[{"type":"string","value":"nam"}],"chức vụ":[{"qualifiers":{"ngày bắt đầu":[{"type":"string","value":"Năm 1400"}],"ngày kết thúc":[{"type":"string","value":"Năm 1401"}]},"type":"string","value":"quốc vương"}],"ngày mất":[{"qualifiers":{"là một":[{"type":"string","value":"tuyên bố trước năm 1584 lịch Gregorius"}]},"type":"string","value":"Ngày 01 Tháng 01 Năm 1407"}],"hình thái chết":[{"type":"string","value":"tử hình"}],"nơi sinh":[{"id":"Q206219","type":"wikibase-item","value":"Hoàng thành Thăng Long"}],"ngày sinh":[{"qualifiers":{"là một":[{"type":"string","value":"tuyên bố trước năm 1584 lịch Gregorius"}]},"type":"string","value":"Ngày 01 Tháng 01 Năm 1336"}],"con cái":[{"id":"Q3269873","type":"wikibase-item","value":"Hồ Hán Thương"},{"type":"string","value":"Hồ Nguyên Trừng"},{"type":"string","value":"Khâm Thánh hoàng hậu"}],"nơi chôn cất":[{"id":"Q206219","type":"wikibase-item","value":"Hoàng thành Thăng Long"}]},"description":"hoàng đế Việt Nam","id":"Q1319152","label":"Hồ Quý Ly"}