{"overview":"Hà Kế Tấn (1912 \u2013 1997) là đảng viên Đảng Cộng sản Việt Nam, Ủy viên Trung ương Đảng khóa IV, Tư lệnh Liên khu III, Bộ trưởng Bộ Thủy lợi, Chủ nhiệm Ủy ban Trị thủy và Khai thác sông Hồng, Bộ trưởng Đặc trách việc khởi công công trình thủy điện sông Đà.","aliases":[],"references":{"dạng luật pháp":[{"type":"string","value":"đảng phái chính trị"}],"thành phố":[{"type":"string","value":"Hà Nội"}],"Ban Chấp hành Trung ương":[{"type":"string","value":"Ban Chấp hành Trung ương Đảng Cộng sản Việt Nam"}],"đập":[{"type":"string","value":"Nhà máy thủy điện Hòa Bình"}],"người":[{"id":"Q10787626","type":"wikibase-item","value":"Lê Hiến Mai"},{"id":"Q20025871","type":"wikibase-item","value":"Lê Tiến Phục"},{"id":"Q10829684","type":"wikibase-item","value":"Trần Đăng Khoa (bộ trưởng)"},{"id":"Q20026229","type":"wikibase-item","value":"Trần Quý Kiên"},{"id":"Q10769012","type":"wikibase-item","value":"Hoàng Sâm"},{"id":"Q10829448","type":"wikibase-item","value":"Trần Quyết"},{"id":"Q25418222","type":"wikibase-item","value":"Nguyễn Thanh Bình"},{"id":"Q10787814","type":"wikibase-item","value":"Lê Thanh Nghị"},{"id":"Q358051","type":"wikibase-item","value":"Phạm Văn Đồng"},{"id":"Q10779534","type":"wikibase-item","value":"Khuất Duy Tiến"},{"id":"Q10805065","type":"wikibase-item","value":"Phan Thanh"}],"huyện":[{"type":"string","value":"Phúc Thọ"}],"xã của Việt Nam":[{"id":"Q10840980","type":"wikibase-item","value":"Đường Lâm"}],"thị xã của Việt Nam":[{"type":"string","value":"Sơn Tây"}],"đảng cộng sản":[{"type":"string","value":"Đảng Cộng sản Việt Nam"}],"sông":[{"type":"string","value":"Sông Hồng"},{"type":"string","value":"Sông Đà"}],"công chức":[{"type":"string","value":"Bộ trưởng Bộ Nông nghiệp và Phát triển nông thôn (Việt Nam)"}],"quốc gia có chủ quyền":[{"type":"string","value":"Việt Nam"}]},"claims":{"ngày mất":[{"source":["Wikipedia"],"type":"string","value":"năm 1997"}],"nơi sinh":[{"source":["Wikipedia"],"type":"string","value":"Đường Lâm (định hướng)"}],"ngày sinh":[{"source":["Wikipedia"],"type":"string","value":"năm 1912"}],"là một":[{"source":["Wikipedia"],"type":"string","value":"người"}],"nơi mất":[{"source":["Wikipedia"],"type":"string","value":"Hà Nội"}]},"description":"","id":"Q18415663","label":"Hà Kế Tấn"}