{"overview":"Nguyễn Văn Hạnh (sinh ngày 6 tháng 1 năm 1959) là một sĩ quan cấp cao trong Quân đội nhân dân Việt Nam, hàm Trung tướng. Ông nguyên là Phó Chánh án Tòa án Nhân dân tối cao, Chánh án Tòa án Quân sự Trung ương Việt Nam.","aliases":[],"references":{"người":[{"id":"Q10799132","type":"wikibase-item","value":"Nguyễn Hòa Bình"},{"id":"Q7847999","type":"wikibase-item","value":"Trương Hòa Bình"}],"tỉnh của Việt Nam":[{"type":"string","value":"Quảng Trị"}]},"claims":{"ngày sinh":[{"type":"string","value":"Ngày 01 Tháng 01 Năm 1959"}],"là một":[{"type":"string","value":"người"}]},"description":"Phó Chánh án tối cao","id":"Q24958790","label":"Nguyễn Văn Hạnh"}