{"overview":"Philipphê Nguyễn Kim Điền (13 tháng 3 năm 1921 \u2013 8 tháng 6 năm 1988) là một giám mục của Giáo hội Công giáo Rôma tại Việt Nam. Ông nguyên là Giám mục chính tòa Tiên khởi Giáo phận Cần Thơ và nguyên Tổng giám mục đô thành Tổng Giáo phận Huế. Khẩu hiệu Giám mục của ông là \"Nên mọi sự cho mọi người\". Ông là giám mục duy nhất trên thế giới xuất thân từ dòng Tiểu Đệ. ","aliases":[],"references":{"đơn vị hành chính":[{"type":"string","value":"Gia Định"}],"giáo phận Công giáo":[{"type":"string","value":"Giáo phận Cần Thơ"},{"type":"string","value":"Giáo phận Vĩnh Long"},{"type":"string","value":"Giáo phận Mỹ Tho"},{"type":"string","value":"Giáo phận Ban Mê Thuột"},{"type":"string","value":"Giáo phận Xuân Lộc"},{"type":"string","value":"Giáo phận Qui Nhơn"},{"type":"string","value":"Giáo phận Thanh Hóa"},{"type":"string","value":"Giáo phận Phan Thiết"},{"type":"string","value":"Giáo phận Phát Diệm"},{"type":"string","value":"Giáo phận Đà Lạt"},{"type":"string","value":"Giáo phận Bắc Ninh"},{"type":"string","value":"Giáo phận Vinh"}],"người":[{"id":"Q16158451","type":"wikibase-item","value":"Phanxicô Xaviê Nguyễn Văn Sang"},{"id":"Q2061481","type":"wikibase-item","value":"Phaolô Nguyễn Văn Hòa"},{"id":"Q192502","type":"wikibase-item","value":"Ngô Đình Diệm"},{"type":"string","value":"Giáo hoàng Gioan XXIII"},{"id":"Q10805173","type":"wikibase-item","value":"Phaolô Nguyễn Văn Bình"},{"id":"Q10779922","type":"wikibase-item","value":"Kim Long (nhạc sĩ)"},{"id":"Q1984424","type":"wikibase-item","value":"Nguyễn Văn Lý"},{"type":"string","value":"Giáo hoàng Gioan Phaolô II"},{"id":"Q738148","type":"wikibase-item","value":"Ngô Đình Thục"},{"id":"Q10761441","type":"wikibase-item","value":"Giacôbê Nguyễn Ngọc Quang"},{"id":"Q739795","type":"wikibase-item","value":"Nguyễn Văn Linh"},{"id":"Q10761658","type":"wikibase-item","value":"Giuse Trần Văn Thiện"},{"id":"Q10824152","type":"wikibase-item","value":"Tađêô Lê Hữu Từ"},{"id":"Q650194","type":"wikibase-item","value":"Ngô Đình Nhu"},{"id":"Q7820703","type":"wikibase-item","value":"Tôn Thất Xứng"},{"id":"Q439381","type":"wikibase-item","value":"Phaolô Lê Đắc Trọng"},{"id":"Q18415879","type":"wikibase-item","value":"Phaolô Huỳnh Đông Các"},{"id":"Q585842","type":"wikibase-item","value":"Antôn Nguyễn Văn Thiện"},{"id":"Q358051","type":"wikibase-item","value":"Phạm Văn Đồng"},{"id":"Q10840034","type":"wikibase-item","value":"Đa Minh Nguyễn Văn Lãng"},{"id":"Q16481302","type":"wikibase-item","value":"Giuse Maria Nguyễn Tùng Cương"},{"id":"Q10805742","type":"wikibase-item","value":"Phêrô Maria Phạm Ngọc Chi"},{"id":"Q983839","type":"wikibase-item","value":"Nguyễn Hữu Thọ"},{"id":"Q1354825","type":"wikibase-item","value":"Giuse Maria Trịnh Như Khuê"},{"id":"Q10805745","type":"wikibase-item","value":"Phêrô Nguyễn Huy Mai"},{"id":"Q714138","type":"wikibase-item","value":"Phaolô Giuse Phạm Đình Tụng"},{"id":"Q24287132","type":"wikibase-item","value":"Giacôbê Lê Văn Mẫn"},{"id":"Q1986594","type":"wikibase-item","value":"Nicôla Huỳnh Văn Nghi"},{"type":"string","value":"Gioan Cassaigne Sanh"},{"id":"Q532238","type":"wikibase-item","value":"Phanxicô Xaviê Nguyễn Văn Thuận"},{"id":"Q16480967","type":"wikibase-item","value":"Phêrô Trần Đình Tứ"},{"id":"Q1371547","type":"wikibase-item","value":"Stêphanô Nguyễn Như Thể"},{"id":"Q1706367","type":"wikibase-item","value":"Giuse Maria Trịnh Văn Căn"},{"id":"Q1460430","type":"wikibase-item","value":"Phaolô Nguyễn Thanh Hoan"}],"ngôn ngữ":[{"type":"string","value":"tiếng Việt"}],"chiến tranh":[{"id":"Q8740","type":"wikibase-item","value":"Chiến tranh Việt Nam"}],"trận đánh":[{"id":"Q697053","type":"wikibase-item","value":"Trận Mậu Thân tại Huế"},{"id":"Q482456","type":"wikibase-item","value":"Sự kiện 30 tháng 4 năm 1975"}],"giáo tỉnh":[{"type":"string","value":"Giáo tỉnh Hà Nội"}],"tỉnh của Việt Nam":[{"type":"string","value":"Trà Vinh"}],"quốc gia có chủ quyền":[{"type":"string","value":"Đức"},{"type":"string","value":"Việt Nam"},{"type":"string","value":"Việt Nam Cộng hòa"}],"đảo chính":[{"id":"Q1078181","type":"wikibase-item","value":"Đảo chính Việt Nam Cộng hòa 1963"}],"cựu quốc gia":[{"id":"Q1072362","type":"wikibase-item","value":"Cộng hòa Miền Nam Việt Nam"}],"nhà thờ chính tòa":[{"id":"Q28197251","type":"wikibase-item","value":"Nhà thờ chính tòa Phủ Cam"},{"id":"Q428129","type":"wikibase-item","value":"Nhà thờ Đức Bà Sài Gòn"}],"xã của Việt Nam":[{"type":"string","value":"Long Đức"}],"Không quân":[{"type":"string","value":"Không lực Việt Nam Cộng hòa"}],"Châu lục":[{"type":"string","value":"châu Âu"}],"thành phố trực thuộc trung ương Việt Nam":[{"type":"string","value":"Thành phố Hồ Chí Minh"}],"tuần báo":[{"type":"string","value":"Việt Báo"}],"thành phố trực thuộc tỉnh Việt Nam":[{"type":"string","value":"Huế"}],"liên bang":[{"type":"string","value":"Liên bang Đông Dương"}],"tổ chức liên chính phủ":[{"type":"string","value":"Liên Hợp Quốc"}],"huyện":[{"type":"string","value":"Di Linh"}],"Đức Mẹ hiện ra":[{"id":"Q781750","type":"wikibase-item","value":"Đức Mẹ La Vang"}],"chức vụ":[{"type":"string","value":"Chủ tịch Quốc hội Việt Nam"}],"bệnh viện":[{"type":"string","value":"Bệnh viện Nguyễn Trãi"},{"type":"string","value":"Bệnh viện Chợ Rẫy"}],"tổ chức":[{"type":"string","value":"Caritas Việt Nam"}],"quận":[{"type":"string","value":"Bình Thủy"}]},"claims":{"nói, viết hoặc ký bằng các ngôn ngữ":[{"source":["Wikipedia"],"type":"string","value":"tiếng Việt"}],"tôn giáo":[{"source":["Wikipedia"],"type":"string","value":"Giáo hội Công giáo Rôma"}],"quốc tịch":[{"source":["Wikipedia"],"type":"string","value":"Việt Nam"}],"nghề nghiệp":[{"qualifiers":{"ngày bắt đầu":[{"type":"string","value":"ngày 21 tháng 07 năm 1947"}]},"source":["Wikipedia"],"type":"string","value":"linh mục Công giáo"}],"là một":[{"source":["Wikipedia"],"type":"string","value":"người"}],"nơi mất":[{"source":["DBPedia"],"type":"string","value":"Thành phố Hồ Chí Minh"}],"giới tính":[{"source":["Wikipedia"],"type":"string","value":"nam"}],"chức vụ":[{"qualifiers":{"ngày bắt đầu":[{"type":"string","value":"năm 1961"}]},"source":["Wikipedia"],"type":"string","value":"giám mục Công giáo"},{"qualifiers":{"ngày bắt đầu":[{"type":"string","value":"ngày 24 tháng 11 năm 1960"}],"số thứ tự trong chuỗi":[{"type":"string","value":"1"}],"được thay thế bởi":[{"id":"Q10761441","type":"wikibase-item","value":"Giacôbê Nguyễn Ngọc Quang"}],"thay thế cho":[{"id":"Q10805173","type":"wikibase-item","value":"Phaolô Nguyễn Văn Bình"}],"giáo phận":[{"id":"Q73816","type":"wikibase-item","value":"Giáo phận Cần Thơ"}]},"source":["Wikipedia"],"type":"string","value":"giám mục chính tòa"},{"qualifiers":{"ngày bắt đầu":[{"type":"string","value":"ngày 11 tháng 03 năm 1968"}],"thay thế cho":[{"id":"Q738148","type":"wikibase-item","value":"Ngô Đình Thục"}],"giáo phận":[{"id":"Q73939","type":"wikibase-item","value":"Tổng giáo phận Huế"}]},"source":["Wikipedia"],"type":"string","value":"tổng giám mục Công giáo"}],"ngày mất":[{"source":["DBPedia","Wikipedia"],"type":"string","value":"ngày 08 tháng 06 năm 1988"}],"nơi sinh":[{"source":["DBPedia"],"type":"string","value":"Trà Vinh"}],"tên":[{"source":["Wikipedia"],"type":"string","value":"Philippe"}],"ngày sinh":[{"source":["DBPedia","Wikipedia"],"type":"string","value":"ngày 13 tháng 03 năm 1921"}],"nơi chôn cất":[{"id":"Q28197251","source":["Wikipedia"],"type":"wikibase-item","value":"Nhà thờ chính tòa Phủ Cam"}]},"description":"giám mục của Giáo hội Công giáo Rôma tại Việt Nam","id":"Q27861862","label":"Philípphê Nguyễn Kim Điền"}