{"overview":"Ngô Sĩ Quý (1922-1997) là một đại võ sư phái Vĩnh Xuân quyền tại Việt Nam, học trò thuộc những thế hệ đầu tiên của tổ sư Vĩnh Xuân quyền Việt Nam Nguyễn Tế Công.","aliases":[],"references":{"thành phố":[{"type":"string","value":"Hà Nội"}],"sắc tộc":[{"type":"string","value":"người Việt"}],"tỉnh của Trung Quốc":[{"type":"string","value":"Quảng Đông"}],"người":[{"id":"Q10769115","type":"wikibase-item","value":"Hoàng Vĩnh Giang"}],"viện đại học":[{"type":"string","value":"Trường Đại học Sư phạm Hà Nội"}],"nhà thờ chính tòa":[{"id":"Q1923783","type":"wikibase-item","value":"Nhà thờ Lớn Hà Nội"}],"đường phố":[{"type":"string","value":"Hàng Bạc"}],"môn thể thao":[{"type":"string","value":"Quyền Anh"}],"nghề nghiệp":[{"type":"string","value":"Võ sư"}],"quốc gia có chủ quyền":[{"type":"string","value":"Trung Quốc"},{"type":"string","value":"Việt Nam"}]},"claims":{"ngày mất":[{"source":["Wikipedia"],"type":"string","value":"năm 1997"}],"ngày sinh":[{"source":["Wikipedia"],"type":"string","value":"năm 1922"}],"là một":[{"source":["Wikipedia"],"type":"string","value":"người"}]},"description":"","id":"Q49055270","label":"Ngô Sĩ Quý"}