{"overview":"Ngô Thị Hoàng Yến là nữ Thiếu tướng Công an nhân dân Việt Nam. Bà hiện giữ chức vụ Cục trưởng Cục Hồ sơ nghiệp vụ, Bộ Công an. Bà nguyên là Phó Cục trưởng Cục Công tác Đảng và công tác chính trị, Bộ Công an. Bà là người phụ nữ trong Công an nhân dân Việt Nam được phong quân hàm tướng, sau các bà (nguyên Phó Cục trưởng Cục Pháp chế và Cải cách thủ tục Hành chính - Tư pháp Thiếu tướng Nguyễn Thị Xuân, Cục trưởng Cục Xây dựng Phong trào Toàn dân Bảo vệ An ninh Tổ quốc Trung tướng Trần Thị Ngọc Đẹp, Ủy viên Ủy ban Kiểm tra Đảng ủy Công an TW Thiếu tướng Hoàng Thị Thủy, Giám đốc Công an tỉnh Kiên Giang Thiếu tướng Bùi Tuyết Minh, Phó Cục trưởng Cục Cảnh sát phòng chống tội phạm môi trường Thiếu tướng Nhữ Thị Minh Nguyệt, Cục trưởng Cục Hồ sơ nghiệp vụ Thiếu tướng Ngô Thị Hoàng Yến, Phó Cục trưởng Cục Kế hoạch và Tài chính Thiếu tướng Nguyễn Thị Kim Dung, Phó Cục trưởng Cục An ninh chính trị nội bộ Thiếu tướng Trần Thị Bé Nhân, Cục trưởng Cục Y tế Thiếu tướng Phạm Thị Lan Anh).","aliases":[],"references":{"dạng luật pháp":[{"type":"string","value":"đảng phái chính trị"}],"bộ công an":[{"type":"string","value":"Bộ Công an"}],"người":[{"id":"Q30921212","type":"wikibase-item","value":"Nguyễn Thị Xuân"},{"id":"Q10831196","type":"wikibase-item","value":"Tô Lâm"}],"quân hàm cảnh sát":[{"type":"string","value":"Thiếu tướng Công an Nhân dân Việt Nam"}],"đảng cộng sản":[{"type":"string","value":"Đảng Cộng sản Việt Nam"}]},"claims":{"quốc tịch":[{"source":["Wikipedia"],"type":"string","value":"Việt Nam"}],"là một":[{"source":["Wikipedia"],"type":"string","value":"người"}]},"description":"","id":"Q86010663","label":"Ngô Thị Hoàng Yến"}